{"cameraMode":{"drawMode":0,"name":"Shaded","section":"Shading Mode"},"sceneLighting":true,"audioPlay":false,"sceneViewState":{"m_AlwaysRefresh":false,"showFog":true,"showSkybox":true,"showFlares":true,"showImageEffects":true,"showParticleSystems":true,"showVisualEffectGraphs":true,"m_FxEnabled":true},"in2DMode":false,"pivot":{"x":393.0543212890625,"y":266.3138427734375,"z":27.4927978515625},"rotation":{"x":0.11253973841667175,"y":0.02384338714182377,"z":-0.0026949546299874784,"w":0.9933822154998779},"size":329.7447509765625,"orthographic":false}